de_transformation/__init__.py
de_transformation/tools.py
de_transformation-0.1.5.dist-info/METADATA
de_transformation-0.1.5.dist-info/WHEEL
de_transformation-0.1.5.dist-info/RECORD
